teamcity/__init__.py
teamcity/common.py
teamcity/context_managers.py
teamcity/diff_tools.py
teamcity/django.py
teamcity/flake8_plugin.py
teamcity/flake8_v2_plugin.py
teamcity/flake8_v3_plugin.py
teamcity/jb_behave_formatter.py
teamcity/jb_local_exc_store.py
teamcity/messages.py
teamcity/nose_report.py
teamcity/pylint_reporter.py
teamcity/pytest_plugin.py
teamcity/unittestpy.py
twisted/plugins/teamcity_plugin.py
teamcity_messages-1.33.dist-info/LICENSE.md
teamcity_messages-1.33.dist-info/METADATA
teamcity_messages-1.33.dist-info/WHEEL
teamcity_messages-1.33.dist-info/entry_points.txt
teamcity_messages-1.33.dist-info/top_level.txt
teamcity_messages-1.33.dist-info/RECORD
