Metadata-Version: 2.2
Name: teamcity-messages
Version: 1.33
Summary: Send test results to TeamCity continuous integration server from unittest, nose, py.test, twisted trial, behave (Python 2.6+)
Home-page: https://github.com/JetBrains/teamcity-messages
Author: JetBrains
Author-email: teamcity-feedback@jetbrains.com
License: Apache 2.0
Keywords: unittest teamcity test nose behave flake8 py.test pytest jetbrains
Platform: any
Classifier: Development Status :: 5 - Production/Stable
Classifier: Intended Audience :: Developers
Classifier: License :: OSI Approved :: Apache Software License
Classifier: Operating System :: OS Independent
Classifier: Programming Language :: Python
Classifier: Programming Language :: Python :: 2.7
Classifier: Programming Language :: Python :: 3.6
Classifier: Programming Language :: Python :: 3.7
Classifier: Programming Language :: Python :: 3.8
Classifier: Programming Language :: Python :: 3.9
Classifier: Programming Language :: Python :: 3.10
Classifier: Topic :: Software Development :: Testing
License-File: LICENSE.md
Dynamic: author
Dynamic: author-email
Dynamic: classifier
Dynamic: description
Dynamic: home-page
Dynamic: keywords
Dynamic: license
Dynamic: platform
Dynamic: summary
